[
  {
    "title": "Citroën C3 exclusive 1.6i Automatic 29 000 km",
    "price": "€ 3.950,-",
    "mileage": "29.000 km",
    "location": "Tielt",
    "creationDate": "Aujourd'hui",
    "link": "https://www.2ememain.be/v/autos/citroen/m2421336702-citroen-c3-exclusive-1-6i-automatic-29-000-km"
  },
  {
    "title": "Hyundai ACCENT1.6i GLS BENZINE Automaat A/C GEKEURD CAR-PASS",
    "price": "€ 2.500,-",
    "mileage": "128.000 km",
    "location": "Lubbeek",
    "creationDate": "Aujourd'hui",
    "link": "https://www.2ememain.be/v/autos/hyundai/m2421369664-hyundai-accent1-6i-gls-benzine-automaat-a-c-gekeurd-car-pass?_gl=1*ngop0j*_up*MQ..*_ga*MTE3MTU4MjU5OC4xNzg0MzYzMTI4*_ga_HS0GGDE3SH*czE3ODQzNjMxMjQkbzEkZzAkdDE3ODQzNjMxMjQkajYwJGwwJGgxNzY0MDcwNDI0"
  },
  {
    "title": "FIAT PANDA/AUTOMATIQUE/74 000 KM",
    "price": "€ 3.990,-",
    "mileage": "74.000 km",
    "location": "Gent",
    "creationDate": "Aujourd'hui",
    "link": "https://www.2ememain.be/v/autos/fiat/m2421394307-fiat-panda-automatique-74-000-km?_gl=1*1n6qe67*_up*MQ..*_ga*MjA3OTMyOTQ3MS4xNzg0MzY5MDAz*_ga_HS0GGDE3SH*czE3ODQzNjkwMDEkbzEkZzAkdDE3ODQzNjkwMDEkajYwJGwwJGgxNjc2NDg0MDU1"
  },
  {
    "title": "Toyota yaris automatique.003266318536.",
    "price": "€ 2.500,-",
    "mileage": "118 km",
    "location": "Liedekerke +Deel Borchtlombeek",
    "creationDate": "Aujourd'hui",
    "link": "https://www.2ememain.be/v/autos/toyota/m2421379212-toyota-yaris-automatique-003266318536"
  },
  {
    "title": "VW polo 1.4 benzine MPI automaat",
    "price": "€ 1.500,-",
    "mileage": "112.500 km",
    "location": "Leuven",
    "creationDate": "Aujourd'hui",
    "link": "https://www.2ememain.be/v/autos/volkswagen/m2421445035-vw-polo-1-4-benzine-mpi-automaat"
  },
  {
    "title": "Volkswagen Polo 1.4 i Automatic 5 p., Air Co",
    "price": "€ 3.500,-",
    "mileage": "N/A",
    "location": "Dilbeek",
    "creationDate": "Aujourd'hui",
    "link": "https://www.2ememain.be/v/autos/volkswagen/m2421423291-volkswagen-polo-1-4-i-automatic-5-p-air-co"
  },
  {
    "title": "Mini cooper (Pompe de direction à changer)",
    "price": "€ 3.500,-",
    "mileage": "126.780 km",
    "location": "Bruxelles",
    "creationDate": "Aujourd'hui",
    "link": "https://www.2ememain.be/v/autos/mini/m2421501866-mini-cooper-pompe-de-direction-a-changer"
  },
  {
    "title": "Saab 9-5 2.0 T Benzine 2007 / Automaat / Airco",
    "price": "€ 2.490,-",
    "mileage": "102.946 km",
    "location": "Brugge",
    "creationDate": "Aujourd'hui",
    "link": "https://www.2ememain.be/v/autos/saab/m2421515141-saab-9-5-2-0-t-benzine-2007-automaat-airco?_gl=1*8w9qt5*_up*MQ..*_ga*MTgwMDI2NzA0LjE3ODQzODMzNTM.*_ga_HS0GGDE3SH*czE3ODQzODMzNTEkbzEkZzAkdDE3ODQzODMzNTEkajYwJGwwJGg1NDQ2ODc2MDI."
  },
  {
    "title": "Peugeot 206 CC—1.6Essence automatique 140000km Prêt à rouler",
    "price": "€ 3.550,-",
    "mileage": "140.000 km",
    "location": "Meise + Deel Van Brussegem",
    "creationDate": "Aujourd'hui",
    "link": "https://www.2ememain.be/v/autos/peugeot/m2421481569-peugeot-206-cc-1-6essence-automatique-140000km-pret-a-rouler?_gl=1*8o1naj*_up*MQ..*_ga*NjYxNDQ5ODkxLjE3ODQzODMzNTk.*_ga_HS0GGDE3SH*czE3ODQzODMzNTYkbzEkZzAkdDE3ODQzODMzNTYkajYwJGwwJGgxNzE0MTU4NTI4"
  }
]